mooncake/__init__.py
mooncake/allocator.py
mooncake/async_store.py
mooncake/cli.py
mooncake/cli_bench.py
mooncake/cli_client.py
mooncake/engine.so
mooncake/ep.py
mooncake/http_metadata_server.py
mooncake/mooncake_client
mooncake/mooncake_config.py
mooncake/mooncake_connector_v1.py
mooncake/mooncake_ep_buffer.py
mooncake/mooncake_master
mooncake/mooncake_store_service.py
mooncake/nvlink_allocator.so
mooncake/store.so
mooncake/transfer_engine_bench
mooncake/transfer_engine_topology_dump.py
mooncake/vllm_v1_proxy_server.py
mooncake_transfer_engine.libs/libgflags-8661e189.so.2.2.2
mooncake_transfer_engine.libs/libglog-bb9621e6.so.0.4.0
mooncake_transfer_engine.libs/libjsoncpp-b4b91bd8.so.1.9.5
mooncake_transfer_engine.libs/libyaml-cpp-1f8382c1.so.0.7.0
mooncake_transfer_engine-0.3.8.post1.dist-info/METADATA
mooncake_transfer_engine-0.3.8.post1.dist-info/WHEEL
mooncake_transfer_engine-0.3.8.post1.dist-info/entry_points.txt
mooncake_transfer_engine-0.3.8.post1.dist-info/top_level.txt
mooncake_transfer_engine-0.3.8.post1.dist-info/RECORD
